{
  "name": "Date Hierarchy",
  "lineageTag": "98bfbc11-92ac-4b3a-a92a-fdaff5fa1dc2",
  "levels": [
    {
      "name": "Year",
      "ordinal": 0,
      "column": "Year",
      "lineageTag": "35afeb9b-8f6f-49ff-ab58-b9fc9c20276c"
    },
    {
      "name": "Quarter",
      "ordinal": 1,
      "column": "Quarter",
      "lineageTag": "ab055208-1b06-4523-9377-a89b5290552d"
    },
    {
      "name": "Month",
      "ordinal": 2,
      "column": "Month",
      "lineageTag": "d57b099c-8575-4002-83ec-d86391e1472a"
    },
    {
      "name": "Day",
      "ordinal": 3,
      "column": "Day",
      "lineageTag": "354408e1-c79a-4fdd-a50c-d9529f324dec"
    }
  ],
  "annotations": [
    {
      "name": "TemplateId",
      "value": "DateHierarchy"
    }
  ]
}