{
  "name": "Date Hierarchy",
  "lineageTag": "15f3d6bb-6add-4321-9941-21275a79124d",
  "levels": [
    {
      "name": "Year",
      "ordinal": 0,
      "column": "Year",
      "lineageTag": "d324ea51-5be1-4dab-9852-65cdb7057e1c"
    },
    {
      "name": "Quarter",
      "ordinal": 1,
      "column": "Quarter",
      "lineageTag": "de951820-47cc-499c-ab97-1eddc2368760"
    },
    {
      "name": "Month",
      "ordinal": 2,
      "column": "Month",
      "lineageTag": "1cefb1ac-f13d-4850-b83c-118f02f3f509"
    },
    {
      "name": "Day",
      "ordinal": 3,
      "column": "Day",
      "lineageTag": "2992db41-5fa0-4db4-8dd7-23d20fa97db0"
    }
  ],
  "annotations": [
    {
      "name": "TemplateId",
      "value": "DateHierarchy"
    }
  ]
}