{
  "name": "Date Hierarchy",
  "lineageTag": "9e118777-e470-4733-ba74-17071f7d30e0",
  "levels": [
    {
      "name": "Year",
      "ordinal": 0,
      "column": "Year",
      "lineageTag": "8dcaa569-1dd1-46ee-b315-0b838177dae9"
    },
    {
      "name": "Quarter",
      "ordinal": 1,
      "column": "Quarter",
      "lineageTag": "17b86745-796b-4b91-aabb-3cdcf67c9ee2"
    },
    {
      "name": "Month",
      "ordinal": 2,
      "column": "Month",
      "lineageTag": "9cbf4eaa-6f62-412b-a9be-67ed1bc6d2f7"
    },
    {
      "name": "Day",
      "ordinal": 3,
      "column": "Day",
      "lineageTag": "669f4f8e-0c79-4802-a0ed-5203926c646c"
    }
  ],
  "annotations": [
    {
      "name": "TemplateId",
      "value": "DateHierarchy"
    }
  ]
}