{
  "name": "Date Hierarchy",
  "lineageTag": "2f879476-35eb-480f-840f-221bd383023c",
  "levels": [
    {
      "name": "Year",
      "ordinal": 0,
      "column": "Year",
      "lineageTag": "3364ddaf-154b-4803-aca4-12926fb34e01"
    },
    {
      "name": "Quarter",
      "ordinal": 1,
      "column": "Quarter",
      "lineageTag": "a99d1d5a-b03d-44a7-8466-95a44640c7b9"
    },
    {
      "name": "Month",
      "ordinal": 2,
      "column": "Month",
      "lineageTag": "9df2bee2-6fc7-47ac-a2d6-cbdedd178418"
    },
    {
      "name": "Day",
      "ordinal": 3,
      "column": "Day",
      "lineageTag": "b8da30e9-6cb6-4337-8592-a69b0b3574b7"
    }
  ],
  "annotations": [
    {
      "name": "TemplateId",
      "value": "DateHierarchy"
    }
  ]
}