{
  "name": "Date Hierarchy",
  "lineageTag": "f3a7730e-526d-4fb8-b1ba-cbf1b6f540ac",
  "levels": [
    {
      "name": "Year",
      "ordinal": 0,
      "column": "Year",
      "lineageTag": "893ee24e-8369-4415-97b4-4908b87f8df8"
    },
    {
      "name": "Quarter",
      "ordinal": 1,
      "column": "Quarter",
      "lineageTag": "bf761dc5-65fc-4297-88b2-04e6322c483e"
    },
    {
      "name": "Month",
      "ordinal": 2,
      "column": "Month",
      "lineageTag": "1ebdf26c-3dcc-4df8-a7c3-0e25c21313e1"
    },
    {
      "name": "Day",
      "ordinal": 3,
      "column": "Day",
      "lineageTag": "74b46058-528d-4dd4-a42b-93a689c955d0"
    }
  ],
  "annotations": [
    {
      "name": "TemplateId",
      "value": "DateHierarchy"
    }
  ]
}