{
  "name": "Date Hierarchy",
  "lineageTag": "f246748f-37bd-437a-a19d-e3fb22590756",
  "levels": [
    {
      "name": "Year",
      "ordinal": 0,
      "column": "Year",
      "lineageTag": "a44ea4ed-de97-4d40-9e9d-ba007cbba2e0"
    },
    {
      "name": "Quarter",
      "ordinal": 1,
      "column": "Quarter",
      "lineageTag": "e3a38959-148b-4510-89f9-153ab92d920c"
    },
    {
      "name": "Month",
      "ordinal": 2,
      "column": "Month",
      "lineageTag": "24c9a215-8a00-4041-a74f-96bdc129c9d8"
    },
    {
      "name": "Day",
      "ordinal": 3,
      "column": "Day",
      "lineageTag": "2c7bde80-2af4-414d-8f8e-891d6cef42b5"
    }
  ],
  "annotations": [
    {
      "name": "TemplateId",
      "value": "DateHierarchy"
    }
  ]
}